tinytopics/__init__.py
tinytopics/colors.py
tinytopics/data.py
tinytopics/fit.py
tinytopics/fit_distributed.py
tinytopics/loss.py
tinytopics/models.py
tinytopics/plot.py
tinytopics/utils.py
tinytopics-0.9.0.dist-info/METADATA
tinytopics-0.9.0.dist-info/WHEEL
tinytopics-0.9.0.dist-info/licenses/LICENSE
tinytopics-0.9.0.dist-info/RECORD
