Metadata-Version: 2.4
Name: tinytopics
Version: 0.9.0
Summary: Topic modeling via sum-to-one constrained neural Poisson non-negative matrix factorization
Project-URL: Homepage, https://nanx.me/tinytopics/
Project-URL: Documentation, https://nanx.me/tinytopics/
Project-URL: Repository, https://github.com/nanxstats/tinytopics
Project-URL: Issues, https://github.com/nanxstats/tinytopics/issues
Project-URL: Changelog, https://github.com/nanxstats/tinytopics/blob/main/CHANGELOG.md
Author-email: Nan Xiao <me@nanx.me>
License-File: LICENSE
Classifier: Development Status :: 3 - Alpha
Classifier: Intended Audience :: Developers
Classifier: Intended Audience :: Education
Classifier: Intended Audience :: Science/Research
Classifier: License :: OSI Approved :: MIT License
Classifier: Operating System :: OS Independent
Classifier: Programming Language :: Python :: 3
Classifier: Programming Language :: Python :: 3.10
Classifier: Programming Language :: Python :: 3.11
Classifier: Programming Language :: Python :: 3.12
Classifier: Programming Language :: Python :: 3.13
Classifier: Programming Language :: Python :: 3.14
Classifier: Topic :: Scientific/Engineering
Classifier: Topic :: Scientific/Engineering :: Artificial Intelligence
Classifier: Topic :: Scientific/Engineering :: Mathematics
Classifier: Typing :: Typed
Requires-Python: >=3.10
Requires-Dist: accelerate>=1.2.1
Requires-Dist: matplotlib>=3.8.4
Requires-Dist: numpy>=2.0.0
Requires-Dist: scikit-image>=0.22.0
Requires-Dist: scipy>=1.13.0
Requires-Dist: torch>=2.3.0; python_version < '3.13'
Requires-Dist: torch>=2.6.0; python_version >= '3.13'
Requires-Dist: torch>=2.9.0; python_version >= '3.14'
Requires-Dist: tqdm>=4.65.0
